Lint/__init__.py
Lint/pylintrc
Lint/src/__init__.py
Lint/src/Console/Kernel.py
Lint/src/Console/__init__.py
Lint/src/Console/Commands/LintCommand.py
Lint/src/Console/Commands/__init__.py
Lint/src/Console/Commands/Contracts/IConsoleKernel.py
Lint/src/Console/Commands/Contracts/__init__.py
tripteki_pylint-1.0.6.dist-info/LICENSE
tripteki_pylint-1.0.6.dist-info/METADATA
tripteki_pylint-1.0.6.dist-info/WHEEL
tripteki_pylint-1.0.6.dist-info/entry_points.txt
tripteki_pylint-1.0.6.dist-info/top_level.txt
tripteki_pylint-1.0.6.dist-info/RECORD
