Metadata-Version: 2.1
Name: tripteki-pylint
Version: 1.0.6
Summary: Trip Teknologi's Codebase Convention
Author-email: Trip Teknologi <tripteki.company@gmail.com>
License: MIT License
Project-URL: homepage, https://github.com/tripteki/convention-py
Project-URL: bug, https://github.com/tripteki/convention-py/issues
Classifier: Programming Language :: Python :: 3.10
Classifier: Topic :: Software Development :: Libraries :: Python Modules
Requires-Python: >=3.10.0
License-File: LICENSE
Requires-Dist: pylint (>=2.15.5)
